pykemen/__init__.py
pykemen/utilities.py
pykemen/google/__init__.py
pykemen/google/analytics_manager.py
pykemen/google/bigquery_manager.py
pykemen/google/mail_manager.py
pykemen-0.2.22.dist-info/METADATA
pykemen-0.2.22.dist-info/WHEEL
pykemen-0.2.22.dist-info/top_level.txt
pykemen-0.2.22.dist-info/RECORD
