Metadata-Version: 2.1
Name: pykemen
Version: 0.2.22
Summary: Added file attatchemn support to emails
Home-page: https://github.com/ayyoubmarroun/pykemen
Author: Ayyoub Marroun
Author-email: ayyoub@metriplica.com
License: Eiup
Download-URL: https://github.com/ayyoubmarroun/pykemen/archive/0.2.22.tar.gz
Keywords: google apis,utilities
Platform: UNKNOWN
Requires-Dist: httplib2
Requires-Dist: pandas
Requires-Dist: google-api-python-client
Requires-Dist: oauth2client
Requires-Dist: google-cloud
Requires-Dist: google-cloud-core
Requires-Dist: google-cloud-bigquery
Requires-Dist: future
